{"streams":[{"_id":"6531d03899ea6","id":1,"title":"Racing Montevideo \ud83c\udd9a Fenix","browser_uuid":"https:\/\/www.monlive.info\/4500-regarder-racing-montevideo-fenix-en-streaming-campeonato-uruguayo.html","live":["https:\/\/www.prime-sport.info\/hola.php?id=1\/119","https:\/\/www.prime-sport.info\/hola.php?id=2\/119","https:\/\/www.prime-sport.info\/hola.php?id=3\/119","https:\/\/www.prime-sport.info\/hola.php?id=4\/119","https:\/\/www.prime-sport.info\/hola.php?id=5\/119"]},{"_id":"6531d038cccae","id":2,"title":"Colomiers Rugby \ud83c\udd9a Soyaux Angoul\u00eame","browser_uuid":"https:\/\/www.monlive.info\/4501-regarder-colomiers-rugby-soyaux-angoul\u00eame-en-streaming-pro-d2.html","live":["https:\/\/www.prime-sport.info\/hola.php?id=1\/6","https:\/\/www.prime-sport.info\/hola.php?id=2\/6","https:\/\/www.prime-sport.info\/hola.php?id=3\/6","https:\/\/www.prime-sport.info\/hola.php?id=4\/6","https:\/\/www.prime-sport.info\/hola.php?id=5\/6"]},{"_id":"6531d0390b115","id":3,"title":"FC Grenoble \ud83c\udd9a US Montauban","browser_uuid":"https:\/\/www.monlive.info\/4502-regarder-fc-grenoble-us-montauban-en-streaming-pro-d2.html","live":["https:\/\/www.prime-sport.info\/hola.php?id=1\/31","https:\/\/www.prime-sport.info\/hola.php?id=2\/31","https:\/\/www.prime-sport.info\/hola.php?id=3\/31","https:\/\/www.prime-sport.info\/hola.php?id=4\/31","https:\/\/www.prime-sport.info\/hola.php?id=5\/31"]},{"_id":"6531d0393e26e","id":4,"title":"Provence Rugby \ud83c\udd9a AS B\u00e9ziers","browser_uuid":"https:\/\/www.monlive.info\/4503-regarder-provence-rugby-as-b\u00e9ziers-en-streaming-pro-d2.html","live":["https:\/\/www.prime-sport.info\/hola.php?id=1\/32","https:\/\/www.prime-sport.info\/hola.php?id=2\/32","https:\/\/www.prime-sport.info\/hola.php?id=3\/32","https:\/\/www.prime-sport.info\/hola.php?id=4\/32","https:\/\/www.prime-sport.info\/hola.php?id=5\/32"]},{"_id":"6531d0396fe77","id":5,"title":"Stade Montois \ud83c\udd9a Valence Romans","browser_uuid":"https:\/\/www.monlive.info\/4504-regarder-stade-montois-valence-romans-en-streaming-pro-d2.html","live":["https:\/\/www.prime-sport.info\/hola.php?id=1\/33","https:\/\/www.prime-sport.info\/hola.php?id=2\/33","https:\/\/www.prime-sport.info\/hola.php?id=3\/33","https:\/\/www.prime-sport.info\/hola.php?id=4\/33","https:\/\/www.prime-sport.info\/hola.php?id=5\/33"]},{"_id":"6531d039a16b9","id":6,"title":"SU Agen \ud83c\udd9a US Dax","browser_uuid":"https:\/\/www.monlive.info\/4505-regarder-su-agen-us-dax-en-streaming-pro-d2.html","live":["https:\/\/www.prime-sport.info\/hola.php?id=1\/34","https:\/\/www.prime-sport.info\/hola.php?id=2\/34","https:\/\/www.prime-sport.info\/hola.php?id=3\/34","https:\/\/www.prime-sport.info\/hola.php?id=4\/34","https:\/\/www.prime-sport.info\/hola.php?id=5\/34"]},{"_id":"6531d039d3272","id":7,"title":"USO Nevers Rugby \ud83c\udd9a Stade Aurillacois","browser_uuid":"https:\/\/www.monlive.info\/4506-regarder-uso-nevers-rugby-stade-aurillacois-en-streaming-pro-d2.html","live":["https:\/\/www.prime-sport.info\/hola.php?id=1\/35","https:\/\/www.prime-sport.info\/hola.php?id=2\/35","https:\/\/www.prime-sport.info\/hola.php?id=3\/35","https:\/\/www.prime-sport.info\/hola.php?id=4\/35","https:\/\/www.prime-sport.info\/hola.php?id=5\/35"]},{"_id":"6531d03a12d7c","id":8,"title":"Maldonado \ud83c\udd9a River Plate","browser_uuid":"https:\/\/www.monlive.info\/4507-regarder-maldonado-river-plate-en-streaming-campeonato-uruguayo.html","live":["https:\/\/www.prime-sport.info\/hola.php?id=1\/119","https:\/\/www.prime-sport.info\/hola.php?id=2\/119","https:\/\/liveon.sx\/flash19","https:\/\/www.prime-sport.info\/hola.php?id=3\/119","https:\/\/www.prime-sport.info\/hola.php?id=4\/119","https:\/\/www.prime-sport.info\/hola.php?id=5\/119"]},{"_id":"6531d03a46ef7","id":9,"title":"Fenerbahce \ud83c\udd9a Lyon-Villeurbanne","browser_uuid":"https:\/\/www.monlive.info\/4508-regarder-fenerbahce-lyon-villeurbanne-en-streaming-euroligue.html","live":["https:\/\/www.prime-sport.info\/hola.php?id=1\/69","https:\/\/www.prime-sport.info\/hola.php?id=2\/69","https:\/\/liveon.sx\/flash20","https:\/\/www.prime-sport.info\/hola.php?id=3\/69","https:\/\/www.prime-sport.info\/hola.php?id=4\/69","https:\/\/www.prime-sport.info\/hola.php?id=5\/69"]},{"_id":"6531d03a79cdc","id":10,"title":"Olympiakos \ud83c\udd9a Partizan","browser_uuid":"https:\/\/www.monlive.info\/4509-regarder-olympiakos-partizan-en-streaming-euroligue.html","live":["https:\/\/www.prime-sport.info\/hola.php?id=1\/68","https:\/\/www.prime-sport.info\/hola.php?id=2\/68","https:\/\/liveon.sx\/flash24","https:\/\/www.prime-sport.info\/hola.php?id=3\/68","https:\/\/www.prime-sport.info\/hola.php?id=4\/68","https:\/\/www.prime-sport.info\/hola.php?id=5\/68"]},{"_id":"6531d03aacc32","id":11,"title":"Baskonia \ud83c\udd9a Zalgiris Kaunas","browser_uuid":"https:\/\/www.monlive.info\/4510-regarder-baskonia-zalgiris-kaunas-en-streaming-euroligue.html","live":["https:\/\/www.prime-sport.info\/hola.php?id=1\/67","https:\/\/www.prime-sport.info\/hola.php?id=2\/67","https:\/\/liveon.sx\/flash25","https:\/\/www.prime-sport.info\/hola.php?id=3\/67","https:\/\/www.prime-sport.info\/hola.php?id=4\/67","https:\/\/www.prime-sport.info\/hola.php?id=5\/67"]},{"_id":"6531d03adfc31","id":12,"title":"Real Madrid \ud83c\udd9a Milano","browser_uuid":"https:\/\/www.monlive.info\/4511-regarder-real-madrid-milano-en-streaming-euroligue.html","live":["https:\/\/www.prime-sport.info\/hola.php?id=1\/71","https:\/\/www.prime-sport.info\/hola.php?id=2\/71","https:\/\/liveon.sx\/flash21","https:\/\/www.prime-sport.info\/hola.php?id=3\/71","https:\/\/liveon.sx\/flash30","https:\/\/www.prime-sport.info\/hola.php?id=4\/71","https:\/\/www.prime-sport.info\/hola.php?id=5\/71"]},{"_id":"6531d03b1dfe9","id":13,"title":"RC Vannes \ud83c\udd9a Biarritz Olympique","browser_uuid":"https:\/\/www.monlive.info\/4513-regarder-rc-vannes-biarritz-olympique-en-streaming-pro-d2.html","live":["https:\/\/www.prime-sport.info\/hola.php?id=1\/6","https:\/\/www.prime-sport.info\/hola.php?id=2\/6","https:\/\/cdn1.link\/ch9","https:\/\/www.prime-sport.info\/hola.php?id=3\/6","https:\/\/www.prime-sport.info\/hola.php?id=4\/6","https:\/\/www.prime-sport.info\/hola.php?id=5\/6"]},{"_id":"6531d03b4ffe3","id":14,"title":"Gimnasia L.P. \ud83c\udd9a Argentinos Jrs","browser_uuid":"https:\/\/www.monlive.info\/4512-regarder-gimnasia-l-p-argentinos-jrs-en-streaming-torneo-lpf.html","live":["https:\/\/www.prime-sport.info\/hola.php?id=1\/103","https:\/\/www.prime-sport.info\/hola.php?id=2\/103","https:\/\/liveon.sx\/flash10","https:\/\/www.prime-sport.info\/hola.php?id=3\/103","https:\/\/www.prime-sport.info\/hola.php?id=4\/103","https:\/\/www.prime-sport.info\/hola.php?id=5\/103"]},{"_id":"6531d03b82403","id":15,"title":"Cerro CA \ud83c\udd9a Danubio","browser_uuid":"https:\/\/www.monlive.info\/4514-regarder-cerro-ca-danubio-en-streaming-campeonato-uruguayo.html","live":["https:\/\/www.prime-sport.info\/hola.php?id=1\/119","https:\/\/www.prime-sport.info\/hola.php?id=2\/119","https:\/\/liveon.sx\/flash19","https:\/\/www.prime-sport.info\/hola.php?id=3\/119","https:\/\/www.prime-sport.info\/hola.php?id=4\/119","https:\/\/www.prime-sport.info\/hola.php?id=5\/119"]},{"_id":"6531d03bb434a","id":16,"title":"Colon \ud83c\udd9a River Plate","browser_uuid":"https:\/\/www.monlive.info\/4515-regarder-colon-river-plate-en-streaming-torneo-lpf.html","live":["https:\/\/www.prime-sport.info\/hola.php?id=1\/103","https:\/\/www.prime-sport.info\/hola.php?id=2\/103","https:\/\/www.prime-sport.info\/hola.php?id=3\/103","https:\/\/www.prime-sport.info\/hola.php?id=4\/103","https:\/\/www.prime-sport.info\/hola.php?id=5\/103"]},{"_id":"6531d03be60b7","id":17,"title":"Godoy Cruz \ud83c\udd9a San Lorenzo","browser_uuid":"https:\/\/www.monlive.info\/4516-regarder-godoy-cruz-san-lorenzo-en-streaming-torneo-lpf.html","live":["https:\/\/www.prime-sport.info\/hola.php?id=1\/104","https:\/\/www.prime-sport.info\/hola.php?id=2\/104","https:\/\/liveon.sx\/flash26","https:\/\/www.prime-sport.info\/hola.php?id=3\/104","https:\/\/www.prime-sport.info\/hola.php?id=4\/104","https:\/\/www.prime-sport.info\/hola.php?id=5\/104"]},{"_id":"6531d03c257cd","id":18,"title":"Cruzeiro \ud83c\udd9a Flamengo","browser_uuid":"https:\/\/www.monlive.info\/4517-regarder-cruzeiro-flamengo-en-streaming-brasileir\u00e3o.html","live":["https:\/\/www.prime-sport.info\/hola.php?id=1\/41","https:\/\/www.prime-sport.info\/hola.php?id=2\/41","https:\/\/www.prime-sport.info\/hola.php?id=3\/41","https:\/\/www.prime-sport.info\/hola.php?id=4\/41","https:\/\/www.prime-sport.info\/hola.php?id=5\/41"]},{"_id":"6531d03c59a18","id":19,"title":"Palmeiras \ud83c\udd9a Atletico-MG","browser_uuid":"https:\/\/www.monlive.info\/4518-regarder-palmeiras-atletico-mg-en-streaming-brasileir\u00e3o.html","live":["https:\/\/www.prime-sport.info\/hola.php?id=1\/42","https:\/\/www.prime-sport.info\/hola.php?id=2\/42","https:\/\/www.prime-sport.info\/hola.php?id=3\/42","https:\/\/www.prime-sport.info\/hola.php?id=4\/42","https:\/\/www.prime-sport.info\/hola.php?id=5\/42"]},{"_id":"6531d03c8caad","id":20,"title":"Santos \ud83c\udd9a Bragantino","browser_uuid":"https:\/\/www.monlive.info\/4519-regarder-santos-bragantino-en-streaming-brasileir\u00e3o.html","live":["https:\/\/www.prime-sport.info\/hola.php?id=1\/43","https:\/\/www.prime-sport.info\/hola.php?id=2\/43","https:\/\/www.prime-sport.info\/hola.php?id=3\/43","https:\/\/www.prime-sport.info\/hola.php?id=4\/43","https:\/\/www.prime-sport.info\/hola.php?id=5\/43"]},{"_id":"6531d03cbe791","id":21,"title":"Charlotte Hornets \ud83c\udd9a Boston Celtics","browser_uuid":"https:\/\/www.monlive.info\/4520-regarder-charlotte-hornets-boston-celtics-en-streaming-nba.html","live":["https:\/\/www.prime-sport.info\/hola.php?id=1\/130","https:\/\/www.prime-sport.info\/hola.php?id=2\/130","https:\/\/www.prime-sport.info\/hola.php?id=3\/130","https:\/\/www.prime-sport.info\/hola.php?id=4\/130","https:\/\/www.prime-sport.info\/hola.php?id=5\/130"]},{"_id":"6531d03cf137a","id":22,"title":"Buffalo Sabres \ud83c\udd9a Calgary Flames","browser_uuid":"https:\/\/www.monlive.info\/4521-regarder-buffalo-sabres-calgary-flames-en-streaming-nhl.html","live":["https:\/\/www.prime-sport.info\/hola.php?id=1\/145","https:\/\/www.prime-sport.info\/hola.php?id=2\/145","https:\/\/www.prime-sport.info\/hola.php?id=3\/145","https:\/\/www.prime-sport.info\/hola.php?id=4\/145","https:\/\/www.prime-sport.info\/hola.php?id=5\/145"]},{"_id":"6531d03d2fa12","id":23,"title":"Florida Panthers \ud83c\udd9a Toronto Maple Leafs","browser_uuid":"https:\/\/www.monlive.info\/4522-regarder-florida-panthers-toronto-maple-leafs-en-streaming-nhl.html","live":["https:\/\/www.prime-sport.info\/hola.php?id=1\/11","https:\/\/www.prime-sport.info\/hola.php?id=2\/11","https:\/\/www.prime-sport.info\/hola.php?id=3\/11","https:\/\/www.prime-sport.info\/hola.php?id=4\/11","https:\/\/www.prime-sport.info\/hola.php?id=5\/11","https:\/\/www.prime-sport.info\/hola.php?id=1\/146","https:\/\/www.prime-sport.info\/hola.php?id=2\/146","https:\/\/www.prime-sport.info\/hola.php?id=3\/146"]},{"_id":"6531d03d62945","id":24,"title":"New York Rangers \ud83c\udd9a Nashville Predators","browser_uuid":"https:\/\/www.monlive.info\/4523-regarder-new-york-rangers-nashville-predators-en-streaming-nhl.html","live":["https:\/\/www.prime-sport.info\/hola.php?id=1\/147","https:\/\/www.prime-sport.info\/hola.php?id=2\/147","https:\/\/www.prime-sport.info\/hola.php?id=3\/147","https:\/\/www.prime-sport.info\/hola.php?id=4\/147","https:\/\/www.prime-sport.info\/hola.php?id=5\/147"]},{"_id":"6531d03d94953","id":25,"title":"Tampa Bay Lightning \ud83c\udd9a Vancouver Canucks","browser_uuid":"https:\/\/www.monlive.info\/4524-regarder-tampa-bay-lightning-vancouver-canucks-en-streaming-nhl.html","live":["https:\/\/www.prime-sport.info\/hola.php?id=1\/148","https:\/\/www.prime-sport.info\/hola.php?id=2\/148","https:\/\/www.prime-sport.info\/hola.php?id=3\/148","https:\/\/www.prime-sport.info\/hola.php?id=4\/148","https:\/\/www.prime-sport.info\/hola.php?id=5\/148"]},{"_id":"6531d03dc83a7","id":26,"title":"Boston River \ud83c\udd9a Nacional","browser_uuid":"https:\/\/www.monlive.info\/4525-regarder-boston-river-nacional-en-streaming-campeonato-uruguayo.html","live":["https:\/\/www.prime-sport.info\/hola.php?id=1\/119","https:\/\/www.prime-sport.info\/hola.php?id=2\/119","https:\/\/www.prime-sport.info\/hola.php?id=3\/119","https:\/\/www.prime-sport.info\/hola.php?id=4\/119","https:\/\/www.prime-sport.info\/hola.php?id=5\/119"]},{"_id":"6531d03e074fe","id":27,"title":"Philadelphia Flyers \ud83c\udd9a Edmonton Oilers","browser_uuid":"https:\/\/www.monlive.info\/4526-regarder-philadelphia-flyers-edmonton-oilers-en-streaming-nhl.html","live":["https:\/\/www.prime-sport.info\/hola.php?id=1\/149","https:\/\/www.prime-sport.info\/hola.php?id=2\/149","https:\/\/www.prime-sport.info\/hola.php?id=3\/149","https:\/\/www.prime-sport.info\/hola.php?id=4\/149","https:\/\/www.prime-sport.info\/hola.php?id=5\/149","https:\/\/www.prime-sport.info\/hola.php?id=1\/110","https:\/\/www.prime-sport.info\/hola.php?id=2\/110","https:\/\/www.prime-sport.info\/hola.php?id=3\/110"]},{"_id":"6531d03e3a702","id":28,"title":"Rosario \ud83c\udd9a Velez Sarsfield","browser_uuid":"https:\/\/www.monlive.info\/4527-regarder-rosario-velez-sarsfield-en-streaming-torneo-lpf.html","live":["https:\/\/www.prime-sport.info\/hola.php?id=1\/104","https:\/\/www.prime-sport.info\/hola.php?id=2\/104","https:\/\/www.prime-sport.info\/hola.php?id=3\/104","https:\/\/www.prime-sport.info\/hola.php?id=4\/104","https:\/\/www.prime-sport.info\/hola.php?id=5\/104"]},{"_id":"6531d03e6d861","id":29,"title":"GP d'Australie. Essais libres 1 des MotoGP","browser_uuid":"https:\/\/www.monlive.info\/4528-regarder-gp-d-australie--essais-libres-1-des-motogp--en-streaming-motogp.html","live":["https:\/\/www.prime-sport.info\/hola.php?id=1\/37","https:\/\/www.prime-sport.info\/hola.php?id=2\/37","https:\/\/www.prime-sport.info\/hola.php?id=3\/37","https:\/\/www.prime-sport.info\/hola.php?id=4\/37","https:\/\/www.prime-sport.info\/hola.php?id=5\/37","https:\/\/www.prime-sport.info\/hola.php?id=1\/81","https:\/\/www.prime-sport.info\/hola.php?id=2\/81","https:\/\/www.prime-sport.info\/hola.php?id=3\/81"]},{"_id":"6531d03ea02b2","id":30,"title":"Sarmiento Junin \ud83c\udd9a Racing Club","browser_uuid":"https:\/\/www.monlive.info\/4529-regarder-sarmiento-junin-racing-club-en-streaming-torneo-lpf.html","live":["https:\/\/www.prime-sport.info\/hola.php?id=1\/103","https:\/\/www.prime-sport.info\/hola.php?id=2\/103","https:\/\/www.prime-sport.info\/hola.php?id=3\/103","https:\/\/www.prime-sport.info\/hola.php?id=4\/103","https:\/\/www.prime-sport.info\/hola.php?id=5\/103"]},{"_id":"6531d03ed2fe9","id":31,"title":"Chicago Bulls \ud83c\udd9a Minnesota Timberwolves","browser_uuid":"https:\/\/www.monlive.info\/4530-regarder-chicago-bulls-minnesota-timberwolves-en-streaming-nba.html","live":["https:\/\/www.prime-sport.info\/hola.php?id=1\/132","https:\/\/www.prime-sport.info\/hola.php?id=2\/132","https:\/\/www.prime-sport.info\/hola.php?id=3\/132","https:\/\/www.prime-sport.info\/hola.php?id=4\/132","https:\/\/www.prime-sport.info\/hola.php?id=5\/132"]},{"_id":"6531d03f11cd1","id":32,"title":"Oklahoma City Thunder \ud83c\udd9a Detroit Pistons","browser_uuid":"https:\/\/www.monlive.info\/4531-regarder-oklahoma-city-thunder-detroit-pistons-en-streaming-nba.html","live":["https:\/\/www.prime-sport.info\/hola.php?id=1\/133","https:\/\/www.prime-sport.info\/hola.php?id=2\/133","https:\/\/www.prime-sport.info\/hola.php?id=3\/133","https:\/\/www.prime-sport.info\/hola.php?id=4\/133","https:\/\/www.prime-sport.info\/hola.php?id=5\/133"]},{"_id":"6531d03f44e41","id":33,"title":"Minnesota Wild \ud83c\udd9a Los Angeles Kings","browser_uuid":"https:\/\/www.monlive.info\/4532-regarder-minnesota-wild-los-angeles-kings-en-streaming-nhl.html","live":["https:\/\/www.prime-sport.info\/hola.php?id=1\/150","https:\/\/www.prime-sport.info\/hola.php?id=2\/150","https:\/\/www.prime-sport.info\/hola.php?id=3\/150","https:\/\/www.prime-sport.info\/hola.php?id=4\/150","https:\/\/www.prime-sport.info\/hola.php?id=5\/150"]},{"_id":"6531d03f79042","id":34,"title":"St. Louis Blues \ud83c\udd9a Arizona Coyotes","browser_uuid":"https:\/\/www.monlive.info\/4533-regarder-st--louis-blues-arizona-coyotes-en-streaming-nhl.html","live":["https:\/\/www.prime-sport.info\/hola.php?id=1\/151","https:\/\/www.prime-sport.info\/hola.php?id=2\/151","https:\/\/www.prime-sport.info\/hola.php?id=3\/151","https:\/\/www.prime-sport.info\/hola.php?id=4\/151","https:\/\/www.prime-sport.info\/hola.php?id=5\/151"]},{"_id":"6531d03fac3b2","id":35,"title":"Winnipeg Jets \ud83c\udd9a Vegas Golden Knights","browser_uuid":"https:\/\/www.monlive.info\/4534-regarder-winnipeg-jets-vegas-golden-knights-en-streaming-nhl.html","live":["https:\/\/www.prime-sport.info\/hola.php?id=1\/152","https:\/\/www.prime-sport.info\/hola.php?id=2\/152","https:\/\/www.prime-sport.info\/hola.php?id=3\/152","https:\/\/www.prime-sport.info\/hola.php?id=4\/152","https:\/\/www.prime-sport.info\/hola.php?id=5\/152"]},{"_id":"6531d03fdf83e","id":36,"title":"New Orleans Saints \ud83c\udd9a Jacksonville Jaguars","browser_uuid":"https:\/\/www.monlive.info\/4535-regarder-new-orleans-saints-jacksonville-jaguars-en-streaming-nfl.html","live":["https:\/\/www.prime-sport.info\/hola.php?id=1\/1","https:\/\/www.prime-sport.info\/hola.php?id=2\/1","https:\/\/www.prime-sport.info\/hola.php?id=3\/1","https:\/\/www.prime-sport.info\/hola.php?id=4\/1","https:\/\/www.prime-sport.info\/hola.php?id=5\/1","https:\/\/www.prime-sport.info\/hola.php?id=1\/140","https:\/\/www.prime-sport.info\/hola.php?id=2\/140","https:\/\/www.prime-sport.info\/hola.php?id=3\/140","https:\/\/www.prime-sport.info\/hola.php?id=1\/111","https:\/\/www.prime-sport.info\/hola.php?id=2\/111","https:\/\/www.prime-sport.info\/hola.php?id=4\/111"]},{"_id":"6531d0401e11a","id":37,"title":"Fluminense \ud83c\udd9a Corinthians","browser_uuid":"https:\/\/www.monlive.info\/4536-regarder-fluminense-corinthians-en-streaming-brasileir\u00e3o.html","live":["https:\/\/www.prime-sport.info\/hola.php?id=1\/44","https:\/\/www.prime-sport.info\/hola.php?id=2\/44","https:\/\/www.prime-sport.info\/hola.php?id=3\/44","https:\/\/www.prime-sport.info\/hola.php?id=4\/44","https:\/\/www.prime-sport.info\/hola.php?id=5\/44","https:\/\/www.prime-sport.info\/hola.php?id=1\/108","https:\/\/www.prime-sport.info\/hola.php?id=2\/108","https:\/\/www.prime-sport.info\/hola.php?id=3\/108"]},{"_id":"6531d04051c1d","id":38,"title":"Pereira \ud83c\udd9a Atl. Nacional","browser_uuid":"https:\/\/www.monlive.info\/4537-regarder-pereira-atl--nacional-en-streaming-copa-colombia.html","live":["https:\/\/www.prime-sport.info\/hola.php?id=1\/120","https:\/\/www.prime-sport.info\/hola.php?id=2\/120","https:\/\/www.prime-sport.info\/hola.php?id=3\/120","https:\/\/www.prime-sport.info\/hola.php?id=4\/120","https:\/\/www.prime-sport.info\/hola.php?id=5\/120"]},{"_id":"6531d04082f99","id":39,"title":"Los Angeles Clippers \ud83c\udd9a Denver Nuggets","browser_uuid":"https:\/\/www.monlive.info\/4538-regarder-los-angeles-clippers-denver-nuggets-en-streaming-nba.html","live":["https:\/\/www.prime-sport.info\/hola.php?id=1\/134","https:\/\/www.prime-sport.info\/hola.php?id=2\/134","https:\/\/www.prime-sport.info\/hola.php?id=3\/134","https:\/\/www.prime-sport.info\/hola.php?id=4\/134","https:\/\/www.prime-sport.info\/hola.php?id=5\/134","https:\/\/www.prime-sport.info\/hola.php?id=1\/116","https:\/\/www.prime-sport.info\/hola.php?id=2\/116","https:\/\/www.prime-sport.info\/hola.php?id=3\/116"]},{"_id":"6531d040b4814","id":40,"title":"Los Angeles Lakers \ud83c\udd9a Phoenix Suns","browser_uuid":"https:\/\/www.monlive.info\/4539-regarder-los-angeles-lakers-phoenix-suns-en-streaming-nba.html","live":["https:\/\/www.prime-sport.info\/hola.php?id=1\/135","https:\/\/www.prime-sport.info\/hola.php?id=2\/135","https:\/\/www.prime-sport.info\/hola.php?id=3\/135","https:\/\/www.prime-sport.info\/hola.php?id=4\/135","https:\/\/www.prime-sport.info\/hola.php?id=5\/135"]},{"_id":"6531d040e85a5","id":41,"title":"Sacramento Kings \ud83c\udd9a Utah Jazz","browser_uuid":"https:\/\/www.monlive.info\/4540-regarder-sacramento-kings-utah-jazz-en-streaming-nba.html","live":["https:\/\/www.prime-sport.info\/hola.php?id=1\/136","https:\/\/www.prime-sport.info\/hola.php?id=2\/136","https:\/\/www.prime-sport.info\/hola.php?id=3\/136","https:\/\/www.prime-sport.info\/hola.php?id=4\/136","https:\/\/www.prime-sport.info\/hola.php?id=5\/136"]},{"_id":"6531d04128df5","id":42,"title":"Anaheim Ducks \ud83c\udd9a Dallas Stars","browser_uuid":"https:\/\/www.monlive.info\/4541-regarder-anaheim-ducks-dallas-stars-en-streaming-nhl.html","live":["https:\/\/www.prime-sport.info\/hola.php?id=1\/153","https:\/\/www.prime-sport.info\/hola.php?id=2\/153","https:\/\/www.prime-sport.info\/hola.php?id=3\/153","https:\/\/www.prime-sport.info\/hola.php?id=4\/153","https:\/\/www.prime-sport.info\/hola.php?id=5\/153"]},{"_id":"6531d0415bc19","id":43,"title":"Seattle Kraken \ud83c\udd9a Carolina Hurricanes","browser_uuid":"https:\/\/www.monlive.info\/4542-regarder-seattle-kraken-carolina-hurricanes-en-streaming-nhl.html","live":["https:\/\/www.prime-sport.info\/hola.php?id=1\/154","https:\/\/www.prime-sport.info\/hola.php?id=2\/154","https:\/\/www.prime-sport.info\/hola.php?id=3\/154","https:\/\/www.prime-sport.info\/hola.php?id=4\/154","https:\/\/www.prime-sport.info\/hola.php?id=5\/154"]},{"_id":"6531d0418e7ff","id":44,"title":"Colorado Avalanche \ud83c\udd9a Chicago Blackhawks","browser_uuid":"https:\/\/www.monlive.info\/4543-regarder-colorado-avalanche-chicago-blackhawks-en-streaming-nhl.html","live":["https:\/\/www.prime-sport.info\/hola.php?id=1\/155","https:\/\/www.prime-sport.info\/hola.php?id=2\/155","https:\/\/www.prime-sport.info\/hola.php?id=3\/155","https:\/\/www.prime-sport.info\/hola.php?id=4\/155","https:\/\/www.prime-sport.info\/hola.php?id=5\/155"]},{"_id":"6531d041bf96d","id":45,"title":"San Jose Sharks \ud83c\udd9a Boston Bruins","browser_uuid":"https:\/\/www.monlive.info\/4544-regarder-san-jose-sharks-boston-bruins-en-streaming-nhl.html","live":["https:\/\/www.prime-sport.info\/hola.php?id=1\/156","https:\/\/www.prime-sport.info\/hola.php?id=2\/156","https:\/\/www.prime-sport.info\/hola.php?id=3\/156","https:\/\/www.prime-sport.info\/hola.php?id=4\/156","https:\/\/www.prime-sport.info\/hola.php?id=5\/156"]}]}