{"streams":[{"_id":"658d2ecf22a8c","id":1,"title":"Dallas Mavericks \ud83c\udd9a Cleveland Cavaliers","browser_uuid":"https:\/\/primefoot.ru\/7023-lien-dallas-mavericks-cleveland-cavaliers-en-streaming-nba.html","live":["https:\/\/primefoot.ru\/hola.php?id=1\/1","https:\/\/primefoot.ru\/hola.php?id=2\/1","https:\/\/primefoot.ru\/hola.php?id=3\/1","https:\/\/primefoot.ru\/hola.php?id=5\/1","https:\/\/primefoot.ru\/hola.php?id=1\/144","https:\/\/primefoot.ru\/hola.php?id=3\/144","https:\/\/primefoot.ru\/hola.php?id=2\/144"]},{"_id":"658d2ecf60571","id":2,"title":"Arizona Coyotes \ud83c\udd9a Colorado Avalanche","browser_uuid":"https:\/\/primefoot.ru\/7024-lien-arizona-coyotes-colorado-avalanche-en-streaming-nhl.html","live":["https:\/\/primefoot.ru\/hola.php?id=1\/145","https:\/\/primefoot.ru\/hola.php?id=2\/145","https:\/\/primefoot.ru\/hola.php?id=3\/145","https:\/\/primefoot.ru\/hola.php?id=5\/145"]},{"_id":"658d2ecf9ef19","id":3,"title":"Chicago Blackhawks \ud83c\udd9a Winnipeg Jets","browser_uuid":"https:\/\/primefoot.ru\/7025-lien-chicago-blackhawks-winnipeg-jets-en-streaming-nhl.html","live":["https:\/\/primefoot.ru\/hola.php?id=1\/146","https:\/\/primefoot.ru\/hola.php?id=2\/146","https:\/\/primefoot.ru\/hola.php?id=3\/146","https:\/\/primefoot.ru\/hola.php?id=5\/146"]},{"_id":"658d2ecfde48a","id":4,"title":"Calgary Flames \ud83c\udd9a Seattle Kraken","browser_uuid":"https:\/\/primefoot.ru\/7026-lien-calgary-flames-seattle-kraken-en-streaming-nhl.html","live":["https:\/\/primefoot.ru\/hola.php?id=1\/147","https:\/\/primefoot.ru\/hola.php?id=2\/147","https:\/\/primefoot.ru\/hola.php?id=3\/147","https:\/\/primefoot.ru\/hola.php?id=5\/147"]},{"_id":"658d2ed02876b","id":5,"title":"Anaheim Ducks \ud83c\udd9a Vegas Golden Knights","browser_uuid":"https:\/\/primefoot.ru\/7027-lien-anaheim-ducks-vegas-golden-knights-en-streaming-nhl.html","live":["https:\/\/primefoot.ru\/hola.php?id=1\/148","https:\/\/primefoot.ru\/hola.php?id=2\/148","https:\/\/primefoot.ru\/hola.php?id=3\/148","https:\/\/primefoot.ru\/hola.php?id=5\/148","https:\/\/primefoot.ru\/hola.php?id=1\/110","https:\/\/primefoot.ru\/hola.php?id=3\/110","https:\/\/primefoot.ru\/hola.php?id=2\/110"]},{"_id":"658d2ed065f74","id":6,"title":"Los Angeles Kings \ud83c\udd9a San Jose Sharks","browser_uuid":"https:\/\/primefoot.ru\/7028-lien-los-angeles-kings-san-jose-sharks-en-streaming-nhl.html","live":["https:\/\/primefoot.ru\/hola.php?id=1\/149","https:\/\/primefoot.ru\/hola.php?id=2\/149","https:\/\/primefoot.ru\/hola.php?id=3\/149","https:\/\/primefoot.ru\/hola.php?id=5\/149"]},{"_id":"658d2ed0a4484","id":7,"title":"Anadolu Efes \ud83c\udd9a Fenerbahce","browser_uuid":"https:\/\/primefoot.ru\/8000-lien-anadolu-efes-fenerbahce-en-streaming-euroligue.html","live":["https:\/\/primefoot.ru\/hola.php?id=1\/45","https:\/\/primefoot.ru\/hola.php?id=2\/45","https:\/\/primefoot.ru\/hola.php?id=3\/45","https:\/\/primefoot.ru\/hola.php?id=5\/45"]},{"_id":"658d2ed0e416a","id":8,"title":"Partizan \ud83c\udd9a Virtus Bologna","browser_uuid":"https:\/\/primefoot.ru\/8001-lien-partizan-virtus-bologna-en-streaming-euroligue.html","live":["https:\/\/primefoot.ru\/hola.php?id=1\/46","https:\/\/primefoot.ru\/hola.php?id=2\/46","https:\/\/primefoot.ru\/hola.php?id=3\/46","https:\/\/primefoot.ru\/hola.php?id=5\/46"]},{"_id":"658d2ed1300d4","id":9,"title":"Zalgiris Kaunas \ud83c\udd9a Maccabi Tel Aviv","browser_uuid":"https:\/\/primefoot.ru\/8002-lien-zalgiris-kaunas-maccabi-tel-aviv-en-streaming-euroligue.html","live":["https:\/\/primefoot.ru\/hola.php?id=1\/47","https:\/\/primefoot.ru\/hola.php?id=2\/47","https:\/\/primefoot.ru\/hola.php?id=3\/47","https:\/\/primefoot.ru\/hola.php?id=5\/47"]},{"_id":"658d2ed16ee16","id":10,"title":"Lyon-Villeurbanne \ud83c\udd9a Real Madrid","browser_uuid":"https:\/\/primefoot.ru\/8003-lien-lyon-villeurbanne-real-madrid-en-streaming-euroligue.html","live":["https:\/\/primefoot.ru\/hola.php?id=1\/67","https:\/\/primefoot.ru\/hola.php?id=2\/67","https:\/\/primefoot.ru\/hola.php?id=3\/67","https:\/\/primefoot.ru\/hola.php?id=5\/67"]},{"_id":"658d2ed1afcc5","id":11,"title":"Panathinaikos \ud83c\udd9a \u00c9toile Rouge Belgrade","browser_uuid":"https:\/\/primefoot.ru\/8004-lien-panathinaikos-\u00c9toile-rouge-belgrade-en-streaming-euroligue.html","live":["https:\/\/primefoot.ru\/hola.php?id=1\/48","https:\/\/primefoot.ru\/hola.php?id=2\/48","https:\/\/primefoot.ru\/hola.php?id=3\/48","https:\/\/primefoot.ru\/hola.php?id=5\/48"]},{"_id":"658d2ed1f3e73","id":12,"title":"Grenade \ud83c\udd9a Tenerife","browser_uuid":"https:\/\/primefoot.ru\/8005-lien-grenade-tenerife-en-streaming-liga-endesa.html","live":["https:\/\/primefoot.ru\/hola.php?id=1\/69","https:\/\/primefoot.ru\/hola.php?id=2\/69","https:\/\/primefoot.ru\/hola.php?id=3\/69","https:\/\/primefoot.ru\/hola.php?id=5\/69"]},{"_id":"658d2ed23edbf","id":13,"title":"Zaragoza \ud83c\udd9a MoraBanc Andorra","browser_uuid":"https:\/\/primefoot.ru\/8006-lien-zaragoza-morabanc-andorra-en-streaming-liga-endesa.html","live":["https:\/\/primefoot.ru\/hola.php?id=1\/70","https:\/\/primefoot.ru\/hola.php?id=2\/70","https:\/\/primefoot.ru\/hola.php?id=3\/70","https:\/\/primefoot.ru\/hola.php?id=5\/70"]},{"_id":"658d2ed27d494","id":14,"title":"Bayern \ud83c\udd9a Valence","browser_uuid":"https:\/\/primefoot.ru\/8007-lien-bayern-valence-en-streaming-euroligue.html","live":["https:\/\/primefoot.ru\/hola.php?id=1\/71","https:\/\/primefoot.ru\/hola.php?id=2\/71","https:\/\/primefoot.ru\/hola.php?id=3\/71","https:\/\/primefoot.ru\/hola.php?id=5\/71"]},{"_id":"658d2ed2bb3e0","id":15,"title":"Milano \ud83c\udd9a Baskonia","browser_uuid":"https:\/\/primefoot.ru\/8008-lien-milano-baskonia-en-streaming-euroligue.html","live":["https:\/\/primefoot.ru\/hola.php?id=1\/68","https:\/\/primefoot.ru\/hola.php?id=2\/68","https:\/\/primefoot.ru\/hola.php?id=3\/68","https:\/\/primefoot.ru\/hola.php?id=5\/68"]},{"_id":"658d2ed304fcb","id":16,"title":"Brighton \ud83c\udd9a Tottenham","browser_uuid":"https:\/\/primefoot.ru\/8009-lien-brighton-tottenham-en-streaming-premier-league.html","live":["https:\/\/primefoot.ru\/hola.php?id=1\/36","https:\/\/primefoot.ru\/hola.php?id=2\/36","https:\/\/primefoot.ru\/hola.php?id=3\/36","https:\/\/primefoot.ru\/hola.php?id=5\/36","https:\/\/primefoot.ru\/hola.php?id=1\/86","https:\/\/primefoot.ru\/hola.php?id=3\/86","https:\/\/primefoot.ru\/hola.php?id=2\/86","https:\/\/primefoot.ru\/hola.php?id=3\/82","https:\/\/primefoot.ru\/hola.php?id=2\/82","https:\/\/primefoot.ru\/hola.php?id=1\/82"]},{"_id":"658d2ed34362e","id":17,"title":"Estrela \ud83c\udd9a Arouca","browser_uuid":"https:\/\/primefoot.ru\/8010-lien-estrela-arouca-en-streaming-liga-portugal-bwin.html","live":["https:\/\/primefoot.ru\/hola.php?id=1\/91","https:\/\/primefoot.ru\/hola.php?id=2\/91","https:\/\/primefoot.ru\/hola.php?id=3\/91","https:\/\/primefoot.ru\/hola.php?id=5\/91"]},{"_id":"658d2ed380601","id":18,"title":"Arsenal \ud83c\udd9a West Ham","browser_uuid":"https:\/\/primefoot.ru\/8011-lien-arsenal-west-ham-en-streaming-premier-league.html","live":["https:\/\/primefoot.ru\/hola.php?id=1\/17","https:\/\/primefoot.ru\/hola.php?id=2\/17","https:\/\/primefoot.ru\/hola.php?id=3\/17","https:\/\/primefoot.ru\/hola.php?id=5\/17","https:\/\/primefoot.ru\/hola.php?id=1\/85","https:\/\/primefoot.ru\/hola.php?id=3\/85","https:\/\/primefoot.ru\/hola.php?id=2\/85","https:\/\/primefoot.ru\/hola.php?id=3\/81","https:\/\/primefoot.ru\/hola.php?id=2\/81","https:\/\/primefoot.ru\/hola.php?id=1\/81"]},{"_id":"658d2ed3bf012","id":19,"title":"Carolina Hurricanes \ud83c\udd9a Montreal Canadiens","browser_uuid":"https:\/\/primefoot.ru\/8012-lien-carolina-hurricanes-montreal-canadiens-en-streaming-nhl.html","live":["https:\/\/primefoot.ru\/hola.php?id=1\/130","https:\/\/primefoot.ru\/hola.php?id=2\/130","https:\/\/primefoot.ru\/hola.php?id=3\/130","https:\/\/primefoot.ru\/hola.php?id=5\/130"]},{"_id":"658d2ed40a013","id":20,"title":"Boston Celtics \ud83c\udd9a Detroit Pistons","browser_uuid":"https:\/\/primefoot.ru\/8013-lien-boston-celtics-detroit-pistons-en-streaming-nba.html","live":["https:\/\/primefoot.ru\/hola.php?id=1\/131","https:\/\/primefoot.ru\/hola.php?id=2\/131","https:\/\/primefoot.ru\/hola.php?id=3\/131","https:\/\/primefoot.ru\/hola.php?id=5\/131"]},{"_id":"658d2ed447148","id":21,"title":"Chicago Bulls \ud83c\udd9a Indiana Pacers","browser_uuid":"https:\/\/primefoot.ru\/8014-lien-chicago-bulls-indiana-pacers-en-streaming-nba.html","live":["https:\/\/primefoot.ru\/hola.php?id=1\/132","https:\/\/primefoot.ru\/hola.php?id=2\/132","https:\/\/primefoot.ru\/hola.php?id=3\/132","https:\/\/primefoot.ru\/hola.php?id=5\/132"]},{"_id":"658d2ed487c57","id":22,"title":"Minnesota Timberwolves \ud83c\udd9a Dallas Mavericks","browser_uuid":"https:\/\/primefoot.ru\/8015-lien-minnesota-timberwolves-dallas-mavericks-en-streaming-nba.html","live":["https:\/\/primefoot.ru\/hola.php?id=1\/10","https:\/\/primefoot.ru\/hola.php?id=2\/10","https:\/\/primefoot.ru\/hola.php?id=3\/10","https:\/\/primefoot.ru\/hola.php?id=5\/10","https:\/\/primefoot.ru\/hola.php?id=1\/133","https:\/\/primefoot.ru\/hola.php?id=3\/133","https:\/\/primefoot.ru\/hola.php?id=2\/133","https:\/\/primefoot.ru\/hola.php?id=3\/67","https:\/\/primefoot.ru\/hola.php?id=2\/67","https:\/\/primefoot.ru\/hola.php?id=1\/67"]},{"_id":"658d2ed4c5994","id":23,"title":"New Orleans Pelicans \ud83c\udd9a Utah Jazz","browser_uuid":"https:\/\/primefoot.ru\/8016-lien-new-orleans-pelicans-utah-jazz-en-streaming-nba.html","live":["https:\/\/primefoot.ru\/hola.php?id=1\/134","https:\/\/primefoot.ru\/hola.php?id=2\/134","https:\/\/primefoot.ru\/hola.php?id=3\/134","https:\/\/primefoot.ru\/hola.php?id=5\/134"]},{"_id":"658d2ed50f800","id":24,"title":"Cleveland Browns \ud83c\udd9a New York Jets","browser_uuid":"https:\/\/primefoot.ru\/8017-lien-cleveland-browns-new-york-jets-en-streaming-nfl.html","live":["https:\/\/primefoot.ru\/hola.php?id=1\/2","https:\/\/primefoot.ru\/hola.php?id=2\/2","https:\/\/primefoot.ru\/hola.php?id=3\/2","https:\/\/primefoot.ru\/hola.php?id=5\/2","https:\/\/primefoot.ru\/hola.php?id=1\/135","https:\/\/primefoot.ru\/hola.php?id=3\/135","https:\/\/primefoot.ru\/hola.php?id=2\/135","https:\/\/primefoot.ru\/hola.php?id=3\/71","https:\/\/primefoot.ru\/hola.php?id=2\/71","https:\/\/primefoot.ru\/hola.php?id=1\/71"]},{"_id":"658d2ed54cee3","id":25,"title":"Denver Nuggets \ud83c\udd9a Memphis Grizzlies","browser_uuid":"https:\/\/primefoot.ru\/8018-lien-denver-nuggets-memphis-grizzlies-en-streaming-nba.html","live":["https:\/\/primefoot.ru\/hola.php?id=1\/136","https:\/\/primefoot.ru\/hola.php?id=2\/136","https:\/\/primefoot.ru\/hola.php?id=3\/136","https:\/\/primefoot.ru\/hola.php?id=5\/136"]},{"_id":"658d2ed58bc86","id":26,"title":"Golden State Warriors \ud83c\udd9a Miami Heat","browser_uuid":"https:\/\/primefoot.ru\/8019-lien-golden-state-warriors-miami-heat-en-streaming-nba.html","live":["https:\/\/primefoot.ru\/hola.php?id=1\/137","https:\/\/primefoot.ru\/hola.php?id=2\/137","https:\/\/primefoot.ru\/hola.php?id=3\/137","https:\/\/primefoot.ru\/hola.php?id=5\/137"]},{"_id":"658d2ed5ca6f3","id":27,"title":"Portland Trail Blazers \ud83c\udd9a San Antonio Spurs","browser_uuid":"https:\/\/primefoot.ru\/8020-lien-portland-trail-blazers-san-antonio-spurs-en-streaming-nba.html","live":["https:\/\/primefoot.ru\/hola.php?id=1\/1","https:\/\/primefoot.ru\/hola.php?id=2\/1","https:\/\/primefoot.ru\/hola.php?id=3\/1","https:\/\/primefoot.ru\/hola.php?id=5\/1","https:\/\/primefoot.ru\/hola.php?id=1\/138","https:\/\/primefoot.ru\/hola.php?id=3\/138","https:\/\/primefoot.ru\/hola.php?id=2\/138"]},{"_id":"658d2ed6150cc","id":28,"title":"Vancouver Canucks \ud83c\udd9a Philadelphia Flyers","browser_uuid":"https:\/\/primefoot.ru\/8021-lien-vancouver-canucks-philadelphia-flyers-en-streaming-nhl.html","live":["https:\/\/primefoot.ru\/hola.php?id=1\/139","https:\/\/primefoot.ru\/hola.php?id=2\/139","https:\/\/primefoot.ru\/hola.php?id=3\/139","https:\/\/primefoot.ru\/hola.php?id=5\/139"]},{"_id":"658d2ed653557","id":29,"title":"Vegas Golden Knights \ud83c\udd9a Los Angeles Kings","browser_uuid":"https:\/\/primefoot.ru\/8022-lien-vegas-golden-knights-los-angeles-kings-en-streaming-nhl.html","live":["https:\/\/primefoot.ru\/hola.php?id=1\/140","https:\/\/primefoot.ru\/hola.php?id=2\/140","https:\/\/primefoot.ru\/hola.php?id=3\/140","https:\/\/primefoot.ru\/hola.php?id=5\/140","https:\/\/primefoot.ru\/hola.php?id=1\/110","https:\/\/primefoot.ru\/hola.php?id=3\/110","https:\/\/primefoot.ru\/hola.php?id=2\/110"]},{"_id":"658d2ed691d3c","id":30,"title":"Los Angeles Lakers \ud83c\udd9a Charlotte Hornets","browser_uuid":"https:\/\/primefoot.ru\/8023-lien-los-angeles-lakers-charlotte-hornets-en-streaming-nba.html","live":["https:\/\/primefoot.ru\/hola.php?id=1\/141","https:\/\/primefoot.ru\/hola.php?id=2\/141","https:\/\/primefoot.ru\/hola.php?id=3\/141","https:\/\/primefoot.ru\/hola.php?id=5\/141"]},{"_id":"658d2ed6cf249","id":31,"title":"San Jose Sharks \ud83c\udd9a Edmonton Oilers","browser_uuid":"https:\/\/primefoot.ru\/8024-lien-san-jose-sharks-edmonton-oilers-en-streaming-nhl.html","live":["https:\/\/primefoot.ru\/hola.php?id=1\/142","https:\/\/primefoot.ru\/hola.php?id=2\/142","https:\/\/primefoot.ru\/hola.php?id=3\/142","https:\/\/primefoot.ru\/hola.php?id=5\/142"]}]}