{"streams":[{"_id":"659cc8823f4d2","id":1,"title":"Milwaukee Bucks \ud83c\udd9a Utah Jazz","browser_uuid":"https:\/\/primefoot.ru\/8510-lien-milwaukee-bucks-utah-jazz-en-streaming-nba.html","live":["https:\/\/primefoot.ru\/hola.php?id=1\/10","https:\/\/primefoot.ru\/hola.php?id=2\/10","https:\/\/primefoot.ru\/hola.php?id=3\/10","https:\/\/primefoot.ru\/hola.php?id=5\/10","https:\/\/primefoot.ru\/hola.php?id=1\/136","https:\/\/primefoot.ru\/hola.php?id=3\/136","https:\/\/primefoot.ru\/hola.php?id=2\/136","https:\/\/primefoot.ru\/hola.php?id=3\/67","https:\/\/primefoot.ru\/hola.php?id=2\/67","https:\/\/primefoot.ru\/hola.php?id=1\/67"]},{"_id":"659cc88275c8c","id":2,"title":"Minnesota Wild \ud83c\udd9a Dallas Stars","browser_uuid":"https:\/\/primefoot.ru\/8511-lien-minnesota-wild-dallas-stars-en-streaming-nhl.html","live":["https:\/\/primefoot.ru\/hola.php?id=1\/137","https:\/\/primefoot.ru\/hola.php?id=2\/137","https:\/\/primefoot.ru\/hola.php?id=3\/137","https:\/\/primefoot.ru\/hola.php?id=5\/137"]},{"_id":"659cc882abca6","id":3,"title":"Colorado Avalanche \ud83c\udd9a Boston Bruins","browser_uuid":"https:\/\/primefoot.ru\/8512-lien-colorado-avalanche-boston-bruins-en-streaming-nhl.html","live":["https:\/\/primefoot.ru\/hola.php?id=1\/138","https:\/\/primefoot.ru\/hola.php?id=2\/138","https:\/\/primefoot.ru\/hola.php?id=3\/138","https:\/\/primefoot.ru\/hola.php?id=5\/138"]},{"_id":"659cc882db40b","id":4,"title":"Los Angeles Clippers \ud83c\udd9a Phoenix Suns","browser_uuid":"https:\/\/primefoot.ru\/8513-lien-los-angeles-clippers-phoenix-suns-en-streaming-nba.html","live":["https:\/\/primefoot.ru\/hola.php?id=1\/1","https:\/\/primefoot.ru\/hola.php?id=2\/1","https:\/\/primefoot.ru\/hola.php?id=3\/1","https:\/\/primefoot.ru\/hola.php?id=5\/1","https:\/\/primefoot.ru\/hola.php?id=1\/139","https:\/\/primefoot.ru\/hola.php?id=3\/139","https:\/\/primefoot.ru\/hola.php?id=2\/139"]},{"_id":"659cc8831774f","id":5,"title":"Zambie \ud83c\udd9a Cameroun","browser_uuid":"https:\/\/primefoot.ru\/3400-lien-zambie-cameroun-en-streaming-amical.html","live":["https:\/\/primefoot.ru\/hola.php?id=1\/40","https:\/\/primefoot.ru\/hola.php?id=2\/40","https:\/\/primefoot.ru\/hola.php?id=3\/40","https:\/\/primefoot.ru\/hola.php?id=5\/40"]},{"_id":"659cc883463c2","id":6,"title":"Alanyaspor \ud83c\udd9a Ankaragucu","browser_uuid":"https:\/\/primefoot.ru\/3401-lien-alanyaspor-ankaragucu-en-streaming-super-lig.html","live":["https:\/\/primefoot.ru\/hola.php?id=1\/93","https:\/\/primefoot.ru\/hola.php?id=2\/93","https:\/\/primefoot.ru\/hola.php?id=3\/93","https:\/\/primefoot.ru\/hola.php?id=5\/93"]},{"_id":"659cc88380112","id":7,"title":"Pendikspor \ud83c\udd9a Antalyaspor","browser_uuid":"https:\/\/primefoot.ru\/3402-lien-pendikspor-antalyaspor-en-streaming-super-lig.html","live":["https:\/\/primefoot.ru\/hola.php?id=1\/94","https:\/\/primefoot.ru\/hola.php?id=2\/94","https:\/\/primefoot.ru\/hola.php?id=3\/94","https:\/\/primefoot.ru\/hola.php?id=5\/94"]},{"_id":"659cc883b4a27","id":8,"title":"Kasimpasa \ud83c\udd9a Basaksehir","browser_uuid":"https:\/\/primefoot.ru\/3403-lien-kasimpasa-basaksehir-en-streaming-super-lig.html","live":["https:\/\/primefoot.ru\/hola.php?id=1\/94","https:\/\/primefoot.ru\/hola.php?id=2\/94","https:\/\/primefoot.ru\/hola.php?id=3\/94","https:\/\/primefoot.ru\/hola.php?id=5\/94"]},{"_id":"659cc883e43e8","id":9,"title":"Rizespor \ud83c\udd9a Besiktas","browser_uuid":"https:\/\/primefoot.ru\/3404-lien-rizespor-besiktas-en-streaming-super-lig.html","live":["https:\/\/primefoot.ru\/hola.php?id=1\/10","https:\/\/primefoot.ru\/hola.php?id=2\/10","https:\/\/primefoot.ru\/hola.php?id=3\/10","https:\/\/primefoot.ru\/hola.php?id=5\/10","https:\/\/primefoot.ru\/hola.php?id=1\/93","https:\/\/primefoot.ru\/hola.php?id=3\/93","https:\/\/primefoot.ru\/hola.php?id=2\/93","https:\/\/primefoot.ru\/hola.php?id=3\/101","https:\/\/primefoot.ru\/hola.php?id=2\/101","https:\/\/primefoot.ru\/hola.php?id=1\/101"]},{"_id":"659cc884223f1","id":10,"title":"Fenerbahce \ud83c\udd9a Partizan","browser_uuid":"https:\/\/primefoot.ru\/3405-lien-fenerbahce-partizan-en-streaming-euroligue.html","live":["https:\/\/primefoot.ru\/hola.php?id=1\/70","https:\/\/primefoot.ru\/hola.php?id=2\/70","https:\/\/primefoot.ru\/hola.php?id=3\/70","https:\/\/primefoot.ru\/hola.php?id=5\/70"]},{"_id":"659cc8845191f","id":11,"title":"Monaco \ud83c\udd9a Baskonia","browser_uuid":"https:\/\/primefoot.ru\/3406-lien-monaco-baskonia-en-streaming-euroligue.html","live":["https:\/\/primefoot.ru\/hola.php?id=1\/69","https:\/\/primefoot.ru\/hola.php?id=2\/69","https:\/\/primefoot.ru\/hola.php?id=3\/69","https:\/\/primefoot.ru\/hola.php?id=5\/69"]},{"_id":"659cc88480653","id":12,"title":"Bayern \ud83c\udd9a Real Madrid","browser_uuid":"https:\/\/primefoot.ru\/3407-lien-bayern-real-madrid-en-streaming-euroligue.html","live":["https:\/\/primefoot.ru\/hola.php?id=1\/67","https:\/\/primefoot.ru\/hola.php?id=2\/67","https:\/\/primefoot.ru\/hola.php?id=3\/67","https:\/\/primefoot.ru\/hola.php?id=5\/67"]},{"_id":"659cc884afb45","id":13,"title":"Panathinaikos \ud83c\udd9a Anadolu Efes","browser_uuid":"https:\/\/primefoot.ru\/3408-lien-panathinaikos-anadolu-efes-en-streaming-euroligue.html","live":["https:\/\/primefoot.ru\/hola.php?id=1\/41","https:\/\/primefoot.ru\/hola.php?id=2\/41","https:\/\/primefoot.ru\/hola.php?id=3\/41","https:\/\/primefoot.ru\/hola.php?id=5\/41"]},{"_id":"659cc884df649","id":14,"title":"Lyon-Villeurbanne \ud83c\udd9a \u00c9toile Rouge Belgrade","browser_uuid":"https:\/\/primefoot.ru\/3409-lien-lyon-villeurbanne-\u00c9toile-rouge-belgrade-en-streaming-euroligue.html","live":["https:\/\/primefoot.ru\/hola.php?id=1\/43","https:\/\/primefoot.ru\/hola.php?id=2\/43","https:\/\/primefoot.ru\/hola.php?id=3\/43","https:\/\/primefoot.ru\/hola.php?id=5\/43"]},{"_id":"659cc88519d3b","id":15,"title":"Milano \ud83c\udd9a Alba Berlin","browser_uuid":"https:\/\/primefoot.ru\/3410-lien-milano-alba-berlin-en-streaming-euroligue.html","live":["https:\/\/primefoot.ru\/hola.php?id=1\/42","https:\/\/primefoot.ru\/hola.php?id=2\/42","https:\/\/primefoot.ru\/hola.php?id=3\/42","https:\/\/primefoot.ru\/hola.php?id=5\/42"]},{"_id":"659cc8854913d","id":16,"title":"Valence \ud83c\udd9a Zalgiris Kaunas","browser_uuid":"https:\/\/primefoot.ru\/3411-lien-valence-zalgiris-kaunas-en-streaming-euroligue.html","live":["https:\/\/primefoot.ru\/hola.php?id=1\/68","https:\/\/primefoot.ru\/hola.php?id=2\/68","https:\/\/primefoot.ru\/hola.php?id=3\/68","https:\/\/primefoot.ru\/hola.php?id=5\/68"]},{"_id":"659cc88577767","id":17,"title":"PSG F \ud83c\udd9a Lille F","browser_uuid":"https:\/\/primefoot.ru\/3412-lien-psg-f-lille-f-en-streaming-d1-f\u00e9minine.html","live":["https:\/\/primefoot.ru\/hola.php?id=1\/20","https:\/\/primefoot.ru\/hola.php?id=2\/20","https:\/\/primefoot.ru\/hola.php?id=3\/20","https:\/\/primefoot.ru\/hola.php?id=5\/20"]},{"_id":"659cc885a8701","id":18,"title":"Fiorentina \ud83c\udd9a Bologne","browser_uuid":"https:\/\/primefoot.ru\/3413-lien-fiorentina-bologne-en-streaming-coupe-italie.html","live":["https:\/\/primefoot.ru\/hola.php?id=1\/10","https:\/\/primefoot.ru\/hola.php?id=2\/10","https:\/\/primefoot.ru\/hola.php?id=3\/10","https:\/\/primefoot.ru\/hola.php?id=5\/10","https:\/\/primefoot.ru\/hola.php?id=1\/72","https:\/\/primefoot.ru\/hola.php?id=3\/72","https:\/\/primefoot.ru\/hola.php?id=2\/72","https:\/\/primefoot.ru\/hola.php?id=3\/82","https:\/\/primefoot.ru\/hola.php?id=2\/82","https:\/\/primefoot.ru\/hola.php?id=1\/82"]},{"_id":"659cc885d884d","id":19,"title":"Middlesbrough \ud83c\udd9a Chelsea","browser_uuid":"https:\/\/primefoot.ru\/3414-lien-middlesbrough-chelsea-en-streaming-coupe-de-la-ligue-anglaise.html","live":["https:\/\/primefoot.ru\/hola.php?id=1\/1","https:\/\/primefoot.ru\/hola.php?id=2\/1","https:\/\/primefoot.ru\/hola.php?id=3\/1","https:\/\/primefoot.ru\/hola.php?id=5\/1","https:\/\/primefoot.ru\/hola.php?id=1\/85","https:\/\/primefoot.ru\/hola.php?id=3\/85","https:\/\/primefoot.ru\/hola.php?id=2\/85","https:\/\/primefoot.ru\/hola.php?id=3\/81","https:\/\/primefoot.ru\/hola.php?id=2\/81","https:\/\/primefoot.ru\/hola.php?id=1\/81"]},{"_id":"659cc886142ef","id":20,"title":"Detroit Pistons \ud83c\udd9a Sacramento Kings","browser_uuid":"https:\/\/primefoot.ru\/3415-lien-detroit-pistons-sacramento-kings-en-streaming-nba.html","live":["https:\/\/primefoot.ru\/hola.php?id=1\/130","https:\/\/primefoot.ru\/hola.php?id=2\/130","https:\/\/primefoot.ru\/hola.php?id=3\/130","https:\/\/primefoot.ru\/hola.php?id=5\/130"]},{"_id":"659cc886428e6","id":21,"title":"Orlando Magic \ud83c\udd9a Minnesota Timberwolves","browser_uuid":"https:\/\/primefoot.ru\/3416-lien-orlando-magic-minnesota-timberwolves-en-streaming-nba.html","live":["https:\/\/primefoot.ru\/hola.php?id=1\/10","https:\/\/primefoot.ru\/hola.php?id=2\/10","https:\/\/primefoot.ru\/hola.php?id=3\/10","https:\/\/primefoot.ru\/hola.php?id=5\/10","https:\/\/primefoot.ru\/hola.php?id=1\/131","https:\/\/primefoot.ru\/hola.php?id=3\/131","https:\/\/primefoot.ru\/hola.php?id=2\/131"]},{"_id":"659cc88671b58","id":22,"title":"Buffalo Sabres \ud83c\udd9a Seattle Kraken","browser_uuid":"https:\/\/primefoot.ru\/3417-lien-buffalo-sabres-seattle-kraken-en-streaming-nhl.html","live":["https:\/\/primefoot.ru\/hola.php?id=1\/132","https:\/\/primefoot.ru\/hola.php?id=2\/132","https:\/\/primefoot.ru\/hola.php?id=3\/132","https:\/\/primefoot.ru\/hola.php?id=5\/132"]},{"_id":"659cc886a2e02","id":23,"title":"Tampa Bay Lightning \ud83c\udd9a Los Angeles Kings","browser_uuid":"https:\/\/primefoot.ru\/3418-lien-tampa-bay-lightning-los-angeles-kings-en-streaming-nhl.html","live":["https:\/\/primefoot.ru\/hola.php?id=1\/133","https:\/\/primefoot.ru\/hola.php?id=2\/133","https:\/\/primefoot.ru\/hola.php?id=3\/133","https:\/\/primefoot.ru\/hola.php?id=5\/133"]},{"_id":"659cc886d2fb4","id":24,"title":"Toronto Maple Leafs \ud83c\udd9a San Jose Sharks","browser_uuid":"https:\/\/primefoot.ru\/3419-lien-toronto-maple-leafs-san-jose-sharks-en-streaming-nhl.html","live":["https:\/\/primefoot.ru\/hola.php?id=1\/134","https:\/\/primefoot.ru\/hola.php?id=2\/134","https:\/\/primefoot.ru\/hola.php?id=3\/134","https:\/\/primefoot.ru\/hola.php?id=5\/134"]},{"_id":"659cc8870d5d0","id":25,"title":"New York Knicks \ud83c\udd9a Portland Trail Blazers","browser_uuid":"https:\/\/primefoot.ru\/3420-lien-new-york-knicks-portland-trail-blazers-en-streaming-nba.html","live":["https:\/\/primefoot.ru\/hola.php?id=1\/135","https:\/\/primefoot.ru\/hola.php?id=2\/135","https:\/\/primefoot.ru\/hola.php?id=3\/135","https:\/\/primefoot.ru\/hola.php?id=5\/135"]},{"_id":"659cc887410b2","id":26,"title":"New York Islanders \ud83c\udd9a Vancouver Canucks","browser_uuid":"https:\/\/primefoot.ru\/3421-lien-new-york-islanders-vancouver-canucks-en-streaming-nhl.html","live":["https:\/\/primefoot.ru\/hola.php?id=1\/136","https:\/\/primefoot.ru\/hola.php?id=2\/136","https:\/\/primefoot.ru\/hola.php?id=3\/136","https:\/\/primefoot.ru\/hola.php?id=5\/136"]},{"_id":"659cc88770d35","id":27,"title":"Nashville Predators \ud83c\udd9a Anaheim Ducks","browser_uuid":"https:\/\/primefoot.ru\/3422-lien-nashville-predators-anaheim-ducks-en-streaming-nhl.html","live":["https:\/\/primefoot.ru\/hola.php?id=1\/137","https:\/\/primefoot.ru\/hola.php?id=2\/137","https:\/\/primefoot.ru\/hola.php?id=3\/137","https:\/\/primefoot.ru\/hola.php?id=5\/137"]},{"_id":"659cc887a033c","id":28,"title":"St. Louis Blues \ud83c\udd9a Florida Panthers","browser_uuid":"https:\/\/primefoot.ru\/3423-lien-st--louis-blues-florida-panthers-en-streaming-nhl.html","live":["https:\/\/primefoot.ru\/hola.php?id=1\/139","https:\/\/primefoot.ru\/hola.php?id=2\/139","https:\/\/primefoot.ru\/hola.php?id=3\/139","https:\/\/primefoot.ru\/hola.php?id=5\/139"]},{"_id":"659cc887d0953","id":29,"title":"Winnipeg Jets \ud83c\udd9a Columbus Blue Jackets","browser_uuid":"https:\/\/primefoot.ru\/3424-lien-winnipeg-jets-columbus-blue-jackets-en-streaming-nhl.html","live":["https:\/\/primefoot.ru\/hola.php?id=1\/139","https:\/\/primefoot.ru\/hola.php?id=2\/139","https:\/\/primefoot.ru\/hola.php?id=3\/139","https:\/\/primefoot.ru\/hola.php?id=5\/139"]},{"_id":"659cc8880bc6f","id":30,"title":"Dallas Mavericks \ud83c\udd9a Memphis Grizzlies","browser_uuid":"https:\/\/primefoot.ru\/3425-lien-dallas-mavericks-memphis-grizzlies-en-streaming-nba.html","live":["https:\/\/primefoot.ru\/hola.php?id=1\/1","https:\/\/primefoot.ru\/hola.php?id=2\/1","https:\/\/primefoot.ru\/hola.php?id=3\/1","https:\/\/primefoot.ru\/hola.php?id=5\/1","https:\/\/primefoot.ru\/hola.php?id=1\/140","https:\/\/primefoot.ru\/hola.php?id=3\/140","https:\/\/primefoot.ru\/hola.php?id=2\/140"]},{"_id":"659cc8883b7d4","id":31,"title":"Chicago Blackhawks \ud83c\udd9a Edmonton Oilers","browser_uuid":"https:\/\/primefoot.ru\/3426-lien-chicago-blackhawks-edmonton-oilers-en-streaming-nhl.html","live":["https:\/\/primefoot.ru\/hola.php?id=1\/141","https:\/\/primefoot.ru\/hola.php?id=2\/141","https:\/\/primefoot.ru\/hola.php?id=3\/141","https:\/\/primefoot.ru\/hola.php?id=5\/141"]},{"_id":"659cc8886dd69","id":32,"title":"Arizona Coyotes \ud83c\udd9a Boston Bruins","browser_uuid":"https:\/\/primefoot.ru\/3427-lien-arizona-coyotes-boston-bruins-en-streaming-nhl.html","live":["https:\/\/primefoot.ru\/hola.php?id=1\/142","https:\/\/primefoot.ru\/hola.php?id=2\/142","https:\/\/primefoot.ru\/hola.php?id=3\/142","https:\/\/primefoot.ru\/hola.php?id=5\/142"]},{"_id":"659cc8889c384","id":33,"title":"Calgary Flames \ud83c\udd9a Ottawa Senators","browser_uuid":"https:\/\/primefoot.ru\/3428-lien-calgary-flames-ottawa-senators-en-streaming-nhl.html","live":["https:\/\/primefoot.ru\/hola.php?id=1\/143","https:\/\/primefoot.ru\/hola.php?id=2\/143","https:\/\/primefoot.ru\/hola.php?id=3\/143","https:\/\/primefoot.ru\/hola.php?id=5\/143"]},{"_id":"659cc888cc69e","id":34,"title":"Los Angeles Lakers \ud83c\udd9a Toronto Raptors","browser_uuid":"https:\/\/primefoot.ru\/3429-lien-los-angeles-lakers-toronto-raptors-en-streaming-nba.html","live":["https:\/\/primefoot.ru\/hola.php?id=1\/144","https:\/\/primefoot.ru\/hola.php?id=2\/144","https:\/\/primefoot.ru\/hola.php?id=3\/144","https:\/\/primefoot.ru\/hola.php?id=5\/144"]}]}